experiments/__init__.py
proflow/ProcessRunner.py
proflow/ProcessRunnerCls.py
proflow/ProcessRunner_test.py
proflow/Switch.py
proflow/Switch_test.py
proflow/TimeManager.py
proflow/__init__.py
proflow/config.py
proflow/errors.py
proflow/external_state.py
proflow/grouping.py
proflow/helpers.py
proflow/internal_state.py
proflow/logger.py
proflow/parameters.py
proflow/process_ins_and_outs.py
proflow/process_inspector.py
proflow/process_state_modifiers.py
proflow/version.py
proflow/Objects/Interface.py
proflow/Objects/Process.py
proflow/Objects/__init__.py
proflow/analysis/__init__.py
proflow/analysis/dataflows.py
proflow/analysis/network/__init__.py
proflow/analysis/network/export.py
proflow/analysis/network/extract_nodes_and_edges.py
proflow/analysis/network/extract_nodes_and_edges_test.py
proflow/analysis/webview/__init__.py
proflow/analysis/webview/run_app.py
proflow/tests/Objects_test.py
proflow/tests/TimeManager_test.py
proflow/tests/__init__.py
proflow/tests/conftest.py
proflow/tests/demodata.py
proflow/tests/error_test.py
proflow/tests/grouping_test.py
proflow/tests/helpers_test.py
proflow/tests/logger_test.py
proflow/tests/mocks.py
proflow/tests/optimization_test.py
proflow/tests/parallel_test.py
proflow/tests/process_ins_and_outs_test.py
proflow/tests/process_inspector_test.py
proflow/tests/process_state_modifiers_test.py
proflow/tests/side_effects_test.py
proflow/tests/time_logs_test.py
proflow/tests/snapshots/__init__.py
proflow/tests/snapshots/snap_Objects_test.py
vendor/__init__.py
vendor/helpers/__init__.py
vendor/helpers/comparisons.py
vendor/helpers/comparisons_test.py
vendor/helpers/conftest.py
vendor/helpers/dictionary_helpers.py
vendor/helpers/dictionary_helpers_test.py
vendor/helpers/fill_np_array.py
vendor/helpers/fill_np_array_test.py
vendor/helpers/list_helpers.py
vendor/helpers/named_tuple_helpers.py
vendor/helpers/named_tuple_helpers_test.py
vendor/helpers/time_data.py
vendor/helpers/time_data_test.py
vendor/polyviz/__init__.py
proflow-0.6.6.dist-info/LICENSE
proflow-0.6.6.dist-info/METADATA
proflow-0.6.6.dist-info/WHEEL
proflow-0.6.6.dist-info/top_level.txt
proflow-0.6.6.dist-info/RECORD
