Metadata-Version: 2.1
Name: proflow
Version: 0.6.6
Summary: Functional Process Runner
Author: Sam Bland
Author-email: sbland.co.uk@gmail.com
Classifier: Programming Language :: Python :: 3.7
Classifier: Operating System :: OS Independent
Requires-Python: >=3.8
License-File: LICENSE
Provides-Extra: test
Requires-Dist: pytest ; extra == 'test'
